MANIFEST.in
README.rst
readme.rst
requirements.txt
setup.py
twoline/__init__.py
twoline/cmdline.py
twoline/exceptions.py
twoline/lcd.py
twoline/manager.py
twoline/schema.py
twoline/web.py
twoline.egg-info/PKG-INFO
twoline.egg-info/SOURCES.txt
twoline.egg-info/dependency_links.txt
twoline.egg-info/entry_points.txt
twoline.egg-info/requires.txt
twoline.egg-info/top_level.txt