Metadata-Version: 1.0
Name: twoline
Version: 0.7.8
Summary: Manager for simple character LCDs
Home-page: http://bitbucket.org/latestrevision/twoline/
Author: Adam Coddington
Author-email: me@adamcoddington.net
License: UNKNOWN
Platform: UNKNOWN
Classifier: License :: OSI Approved :: MIT License
Classifier: Operating System :: OS Independent
Classifier: Programming Language :: Python
Classifier: Topic :: Utilities
